aliyunsdkqualitycheck/__init__.py
aliyunsdkqualitycheck/request/__init__.py
aliyunsdkqualitycheck/request/v20190115/AddBusinessCategoryRequest.py
aliyunsdkqualitycheck/request/v20190115/AddRuleCategoryRequest.py
aliyunsdkqualitycheck/request/v20190115/AddThesaurusForApiRequest.py
aliyunsdkqualitycheck/request/v20190115/AssignReviewerRequest.py
aliyunsdkqualitycheck/request/v20190115/CreateAsrVocabRequest.py
aliyunsdkqualitycheck/request/v20190115/CreateSkillGroupConfigRequest.py
aliyunsdkqualitycheck/request/v20190115/CreateTaskAssignRuleRequest.py
aliyunsdkqualitycheck/request/v20190115/CreateUserRequest.py
aliyunsdkqualitycheck/request/v20190115/CreateWarningConfigRequest.py
aliyunsdkqualitycheck/request/v20190115/DelRuleCategoryRequest.py
aliyunsdkqualitycheck/request/v20190115/DelThesaurusForApiRequest.py
aliyunsdkqualitycheck/request/v20190115/DeleteAsrVocabRequest.py
aliyunsdkqualitycheck/request/v20190115/DeleteBusinessCategoryRequest.py
aliyunsdkqualitycheck/request/v20190115/DeleteCustomizationConfigRequest.py
aliyunsdkqualitycheck/request/v20190115/DeleteDataSetRequest.py
aliyunsdkqualitycheck/request/v20190115/DeletePrecisionTaskRequest.py
aliyunsdkqualitycheck/request/v20190115/DeleteScoreForApiRequest.py
aliyunsdkqualitycheck/request/v20190115/DeleteSkillGroupConfigRequest.py
aliyunsdkqualitycheck/request/v20190115/DeleteSubScoreForApiRequest.py
aliyunsdkqualitycheck/request/v20190115/DeleteTaskAssignRuleRequest.py
aliyunsdkqualitycheck/request/v20190115/DeleteUserRequest.py
aliyunsdkqualitycheck/request/v20190115/DeleteWarningConfigRequest.py
aliyunsdkqualitycheck/request/v20190115/EditThesaurusForApiRequest.py
aliyunsdkqualitycheck/request/v20190115/GetAsrVocabRequest.py
aliyunsdkqualitycheck/request/v20190115/GetBusinessCategoryListRequest.py
aliyunsdkqualitycheck/request/v20190115/GetCustomizationConfigListRequest.py
aliyunsdkqualitycheck/request/v20190115/GetHitResultRequest.py
aliyun_python_sdk_qualitycheck-4.7.1.dist-info/LICENSE
aliyun_python_sdk_qualitycheck-4.7.1.dist-info/METADATA
aliyun_python_sdk_qualitycheck-4.7.1.dist-info/WHEEL
aliyun_python_sdk_qualitycheck-4.7.1.dist-info/top_level.txt
aliyun_python_sdk_qualitycheck-4.7.1.dist-info/RECORD
